delairstack_cli/__init__.py
delairstack_cli/analytics.py
delairstack_cli/config.py
delairstack_cli/credentials.py
delairstack_cli/main.py
delairstack_cli/products.py
delairstack_cli/sdk.py
delairstack_cli/share/analytic_schema.yaml
delairstack_cli/utils.py
delairstack_cli-0.3.0.dist-info/entry_points.txt
delairstack_cli-0.3.0.dist-info/WHEEL
delairstack_cli-0.3.0.dist-info/METADATA
delairstack_cli-0.3.0.dist-info/RECORD
