Metadata-Version: 2.1
Name: delairstack-cli
Version: 0.3.0
Summary: CLI for delairstack
License: MIT
Keywords: cli,delair,delair.ai,delairstack
Author: delair.ai Backend Team
Author-email: backend-team@delair.aero
Requires-Python: >=3.6,<4.0
Classifier: License :: OSI Approved :: MIT License
Classifier: Programming Language :: Python :: 3
Classifier: Programming Language :: Python :: 3.6
Classifier: Programming Language :: Python :: 3.7
Classifier: Programming Language :: Python :: 3.8
Requires-Dist: click_spinner (==0.1.8)
Requires-Dist: jsonschema (==3.2.0)
Requires-Dist: python-delairstack (==1.7.8)
Requires-Dist: pyyaml (==5.3.1)
Requires-Dist: tabulate (==0.8.7)
Requires-Dist: typer[all] (==0.1.1)
